LICENSE
MANIFEST.in
fht.c
pyfht.py
setup.py
pyfht.egg-info/PKG-INFO
pyfht.egg-info/SOURCES.txt
pyfht.egg-info/dependency_links.txt
pyfht.egg-info/requires.txt
pyfht.egg-info/top_level.txt