Metadata-Version: 1.1
Name: pyfht
Version: 1.7.0
Summary: Fast Hadamard Transform
Home-page: https://github.com/adamgreig/pyfht
Author: Adam Greig
Author-email: adam@adamgreig.com
License: MIT
Platform: UNKNOWN
Classifier: License :: OSI Approved :: MIT License
Classifier: Programming Language :: Python :: 3.3
Classifier: Programming Language :: Python :: 3.4
Classifier: Topic :: Scientific/Engineering
